LICENSE
README.md
setup.py
manager/__init__.py
manager/main.py
pw_manager_tool.egg-info/PKG-INFO
pw_manager_tool.egg-info/SOURCES.txt
pw_manager_tool.egg-info/dependency_links.txt
pw_manager_tool.egg-info/entry_points.txt
pw_manager_tool.egg-info/requires.txt
pw_manager_tool.egg-info/top_level.txt