Metadata-Version: 2.1
Name: pw-manager-tool
Version: 0.2.4
Summary: Password Manager
Author: scatterman99
Author-email: db.brunetti4@gmail.com
License-File: LICENSE
